sock_python/__init__.py
sock_python/__main__.py
sock_python/_impl.py
sock_python-0.1.1.dist-info/LICENSE
sock_python-0.1.1.dist-info/METADATA
sock_python-0.1.1.dist-info/WHEEL
sock_python-0.1.1.dist-info/top_level.txt
sock_python-0.1.1.dist-info/RECORD
