Metadata-Version: 2.1
Name: sock_python
Version: 0.1.1
Summary: Interactive Python through a network socket
Home-page: https://github.com/hamelin/sock-python
Author: Benoit Hamelin
Author-email: benoit@benoithamelin.com
Classifier: Development Status :: 3 - Alpha
Classifier: Intended Audience :: Developers
Classifier: License :: OSI Approved :: MIT License
Classifier: Programming Language :: Python :: 3
Classifier: Topic :: Software Development :: Interpreters
Requires-Python: >=3.10
License-File: LICENSE
